poridhi_cloud/__init__.py
poridhi_cloud/client.py
poridhi_cloud-0.3.2.dist-info/licenses/LICENSE
poridhi_cloud-0.3.2.dist-info/METADATA
poridhi_cloud-0.3.2.dist-info/WHEEL
poridhi_cloud-0.3.2.dist-info/top_level.txt
poridhi_cloud-0.3.2.dist-info/RECORD
