Metadata-Version: 2.4
Name: poridhi-cloud
Version: 0.3.2
Summary: Python SDK for Poridhi Cloud Infrastructure
Home-page: https://github.com/poridhiEng/poridhi-cloud.git
Author: Poridhi Engineering
Author-email: Poridhi Engineering <engineering@poridhi.com>
License: MIT License
Project-URL: Homepage, https://github.com/poridhiEng/poridhi-cloud-python-sdk
Project-URL: Repository, https://github.com/poridhiEng/poridhi-cloud-python-sdk
Classifier: Development Status :: 3 - Alpha
Classifier: Intended Audience :: Developers
Classifier: License :: OSI Approved :: MIT License
Classifier: Programming Language :: Python :: 3.7
Classifier: Programming Language :: Python :: 3.8
Classifier: Programming Language :: Python :: 3.9
Classifier: Programming Language :: Python :: 3.10
Requires-Python: >=3.7
License-File: LICENSE
Requires-Dist: requests>=2.25.0
Requires-Dist: websocket-client>=1.2.0
Provides-Extra: dev
Requires-Dist: pytest; extra == "dev"
Requires-Dist: pytest-cov; extra == "dev"
Requires-Dist: sphinx; extra == "dev"
Requires-Dist: twine; extra == "dev"
Dynamic: author
Dynamic: home-page
Dynamic: license-file
Dynamic: requires-python
